dbrepo/AmqpClient.py
dbrepo/MqttClient.py
dbrepo/RestClient.py
dbrepo/__init__.py
dbrepo/api/__init__.py
dbrepo/api/dto.py
dbrepo/api/encoder.py
dbrepo/api/exceptions.py
dbrepo/api/mapper.py
dbrepo/api/test.py
dbrepo/core/__init__.py
dbrepo/core/api/__init__.py
dbrepo/core/api/dto.py
dbrepo/core/api/exceptions.py
dbrepo/core/client/__init__.py
dbrepo/core/client/auth.py
dbrepo/core/client/dashboard.py
dbrepo/core/client/search.py
dbrepo/core/client/storage.py
dbrepo/core/omlib/__init__.py
dbrepo/core/omlib/constants.py
dbrepo/core/omlib/dimension.py
dbrepo/core/omlib/measure.py
dbrepo/core/omlib/omconstants.py
dbrepo/core/omlib/scale.py
dbrepo/core/omlib/thing.py
dbrepo/core/omlib/unit.py
dbrepo/core/omlib/exceptions/__init__.py
dbrepo/core/omlib/exceptions/dimensionexception.py
dbrepo/core/omlib/exceptions/unitconversionexception.py
dbrepo/core/omlib/exceptions/unitidentityexception.py
dbrepo/core/omlib/rdf/__init__.py
dbrepo-1.13.2.dist-info/licenses/LICENSE
dbrepo-1.13.2.dist-info/METADATA
dbrepo-1.13.2.dist-info/WHEEL
dbrepo-1.13.2.dist-info/top_level.txt
dbrepo-1.13.2.dist-info/RECORD
