Metadata-Version: 2.4
Name: dbrepo
Version: 1.13.2
Summary: DBRepo Python Library
Home-page: https://www.ifs.tuwien.ac.at/infrastructures/dbrepo/1.13/
Author: Martin Weise
Author-email: "Martin Weise, TU Wien" <martin.weise@tuwien.ac.at>
License-Expression: Apache-2.0
Project-URL: Homepage, https://www.ifs.tuwien.ac.at/infrastructures/dbrepo/1.13/
Project-URL: Documentation, https://www.ifs.tuwien.ac.at/infrastructures/dbrepo/1.13/python/
Project-URL: Issues, https://gitlab.phaidra.org/fair-data-austria-db-repository/fda-services/-/issues
Project-URL: Source, https://gitlab.phaidra.org/fair-data-austria-db-repository/fda-services/
Keywords: DBRepo,Database Repository
Classifier: Development Status :: 4 - Beta
Classifier: Topic :: Software Development :: Libraries
Classifier: Programming Language :: Python :: 3.11
Classifier: Operating System :: OS Independent
Requires-Python: >=3.11
License-File: LICENSE
Requires-Dist: requests>=2.31
Requires-Dist: pika
Requires-Dist: pydantic
Requires-Dist: pandas
Dynamic: author
Dynamic: home-page
Dynamic: license-file
